{
  "images": [
    {
      "id": 1,
      "filename": "wallpaper_girl_1.jpg",
      "path": "https://raw.githubusercontent.com/minhtien379/upload/main/wallpaper/girl/wallpaper_girl_1.jpg",
      "categories": "girl"
    },
    {
      "id": 2,
      "filename": "wallpaper_girl_2.jpg",
      "path": "https://raw.githubusercontent.com/minhtien379/upload/main/wallpaper/girl/wallpaper_girl_2.jpg",
      "categories": "girl"
    },
    {
      "id": 3,
      "filename": "wallpaper_girl_3.jpg",
      "path": "https://raw.githubusercontent.com/minhtien379/upload/main/wallpaper/girl/wallpaper_girl_3.jpg",
      "categories": "girl"
    },
    {
      "id": 4,
      "filename": "wallpaper_girl_4.jpg",
      "path": "https://raw.githubusercontent.com/minhtien379/upload/main/wallpaper/girl/wallpaper_girl_4.jpg",
      "categories": "girl"
    },
    {
      "id": 5,
      "filename": "wallpaper_girl_5.jpg",
      "path": "https://raw.githubusercontent.com/minhtien379/upload/main/wallpaper/girl/wallpaper_girl_5.jpg",
      "categories": "girl"
    },
    {
      "id": 6,
      "filename": "wallpaper_girl_6.jpg",
      "path": "https://raw.githubusercontent.com/minhtien379/upload/main/wallpaper/girl/wallpaper_girl_6.jpg",
      "categories": "girl"
    },
    {
      "id": 7,
      "filename": "wallpaper_girl_7.jpg",
      "path": "https://raw.githubusercontent.com/minhtien379/upload/main/wallpaper/girl/wallpaper_girl_7.jpg",
      "categories": "girl"
    },
    {
      "id": 8,
      "filename": "wallpaper_girl_8.jpg",
      "path": "https://raw.githubusercontent.com/minhtien379/upload/main/wallpaper/girl/wallpaper_girl_8.jpg",
      "categories": "girl"
    },
    {
      "id": 9,
      "filename": "wallpaper_girl_9.jpg",
      "path": "https://raw.githubusercontent.com/minhtien379/upload/main/wallpaper/girl/wallpaper_girl_9.jpg",
      "categories": "girl"
    },
    {
      "id": 10,
      "filename": "wallpaper_girl_10.jpg",
      "path": "https://raw.githubusercontent.com/minhtien379/upload/main/wallpaper/girl/wallpaper_girl_10.jpg",
      "categories": "girl"
    }
  ]
}